{
  "body_parts": [
    { "key": "head",       "label": "头部",  "symptoms": ["头痛","偏头痛","头晕","头胀","头重","头皮麻木"] },
    { "key": "face",       "label": "面部",  "symptoms": ["目眩","眼干","耳鸣","耳聋","鼻塞","口干","口苦","牙痛","面部浮肿"] },
    { "key": "neck",       "label": "颈部",  "symptoms": ["颈部僵硬","颈痛","咽痛","咽干","吞咽困难","颈部淋巴结肿大"] },
    { "key": "shoulder",   "label": "肩部",  "symptoms": ["肩痛","肩周炎","肩部沉重","肩部活动受限"] },
    { "key": "chest",      "label": "胸部",  "symptoms": ["胸闷","胸痛","心悸","气短","咳嗽","咳痰","两肋胀痛"] },
    { "key": "abdomen",    "label": "腹部",  "symptoms": ["胃痛","腹胀","腹痛","恶心","呕吐","食欲不振","便秘","腹泻"] },
    { "key": "waist",      "label": "腰部",  "symptoms": ["腰痛","腰酸","腰部沉重","腰部活动受限"] },
    { "key": "back",       "label": "背部",  "symptoms": ["背痛","背部发凉","背部沉重","脊柱疼痛"] },
    { "key": "upper_limb", "label": "上肢",  "symptoms": ["手指发麻","手指冰凉","手臂酸痛","关节痛","握力减弱","手抖","手指冒凉气"] },
    { "key": "lower_limb", "label": "下肢",  "symptoms": ["腿软","膝痛","小腿抽筋","下肢浮肿","腿部发凉","静脉曲张"] },
    { "key": "foot",       "label": "足部",  "symptoms": ["足跟痛","脚趾麻木","足部冰凉","足底疼痛"] },
    { "key": "whole_body", "label": "全身",  "symptoms": ["畏寒","发热","乏力","盗汗","自汗","失眠","多梦","水肿","体重减轻"] }
  ]
}